calculate_expression/__init__.py
calculate_expression/ce.py
calculate_expression-1.0.9.dist-info/METADATA
calculate_expression-1.0.9.dist-info/WHEEL
calculate_expression-1.0.9.dist-info/top_level.txt
calculate_expression-1.0.9.dist-info/RECORD
