Metadata-Version: 2.1
Name: calculate-expression
Version: 1.0.9
Summary: simple tool to calculate expressions
Home-page: https://github.com/GoodManWEN/calculate_expression
Author: WEN
Author-email: 764499983@qq.com
License: UNKNOWN
Platform: UNKNOWN
Classifier: Programming Language :: Python :: 3
Classifier: License :: OSI Approved :: MIT License
Classifier: Operating System :: OS Independent
